kotti_alert/__init__.py
kotti_alert/__init__.pyc
kotti_alert/events.py
kotti_alert/events.pyc
kotti_alert/fanstatic.py
kotti_alert/fanstatic.pyc
kotti_alert/resources.py
kotti_alert/resources.pyc
kotti_alert/alembic/README
kotti_alert/alembic/env.py
kotti_alert/alembic/script.py.mako
kotti_alert/alembic/versions/.gitkeep
kotti_alert/locale/.gitkeep
kotti_alert/static/js.cookie.js
kotti_alert/static/scripts.js
kotti_alert/static/scripts.min.js
kotti_alert/static/styles.css
kotti_alert/static/styles.min.css
kotti_alert/templates/alert.pt
kotti_alert/templates/list.pt
kotti_alert/templates/message.pt
kotti_alert/tests/conftest.py
kotti_alert/tests/test_functional.py
kotti_alert/tests/test_resources.py
kotti_alert/tests/test_view.py
kotti_alert/views/__init__.py
kotti_alert/views/__init__.pyc
kotti_alert/views/edit.py
kotti_alert/views/edit.pyc
kotti_alert/views/view.py
kotti_alert/views/view.pyc
kotti_alert-0.3.1.dist-info/LICENSE.txt
kotti_alert-0.3.1.dist-info/METADATA
kotti_alert-0.3.1.dist-info/WHEEL
kotti_alert-0.3.1.dist-info/entry_points.txt
kotti_alert-0.3.1.dist-info/top_level.txt
kotti_alert-0.3.1.dist-info/RECORD
