Metadata-Version: 2.1
Name: kotti-alert
Version: 0.3.1
Summary: Alert content type for Kotti
Home-page: https://github.com/b4oshany/kotti_alert
Author: Oshane Bailey
Author-email: b4.oshany@gmail.com
License: BSD-derived (http://www.repoze.org/LICENSE.txt)
Keywords: kotti web cms wcms pylons pyramid sqlalchemy bootstrap alert notification
Platform: UNKNOWN
Classifier: Programming Language :: Python
Classifier: Programming Language :: Python :: 2.7
Classifier: Framework :: Pylons
Classifier: Topic :: Internet :: WWW/HTTP
Classifier: Topic :: Internet :: WWW/HTTP :: Dynamic Content
Classifier: Topic :: Internet :: WWW/HTTP :: WSGI :: Application
Classifier: License :: Repoze Public License
Requires-Dist: Kotti (>=1.0.0)
Requires-Dist: kotti-tinymce
Requires-Dist: kotti-controlpanel (>=1.0.6)
